multiscale_spatial_image/__init__.py
multiscale_spatial_image/_docs.py
multiscale_spatial_image/_version.py
multiscale_spatial_image/multiscale_spatial_image.py
multiscale_spatial_image/utils.py
multiscale_spatial_image/operations/__init__.py
multiscale_spatial_image/operations/operations.py
multiscale_spatial_image/to_multiscale/__init__.py
multiscale_spatial_image/to_multiscale/_dask_image.py
multiscale_spatial_image/to_multiscale/_itk.py
multiscale_spatial_image/to_multiscale/_support.py
multiscale_spatial_image/to_multiscale/_xarray.py
multiscale_spatial_image/to_multiscale/itk_image_to_multiscale.py
multiscale_spatial_image/to_multiscale/to_multiscale.py
multiscale_spatial_image-2.1.0.dist-info/METADATA
multiscale_spatial_image-2.1.0.dist-info/WHEEL
multiscale_spatial_image-2.1.0.dist-info/licenses/LICENSE
multiscale_spatial_image-2.1.0.dist-info/RECORD
