Metadata-Version: 2.4
Name: multiscale_spatial_image
Version: 2.1.0
Summary: Generate a multiscale, chunked, multi-dimensional spatial image data structure that can be serialized to OME-NGFF.
Project-URL: Home, https://github.com/spatial-image/multiscale-spatial-image
Project-URL: Source, https://github.com/spatial-image/multiscale-spatial-image
Project-URL: Issues, https://github.com/spatial-image/multiscale-spatial-image
Author-email: Matt McCormick <matt@mmmccormick.com>
License: 
License-File: LICENSE
Keywords: dask,imaging,itk,ngff,ome,visualization,zarr
Classifier: Intended Audience :: Developers
Classifier: Intended Audience :: Science/Research
Classifier: License :: OSI Approved :: Apache Software License
Classifier: Programming Language :: Python
Classifier: Programming Language :: Python :: 3
Classifier: Programming Language :: Python :: 3.11
Classifier: Programming Language :: Python :: 3.12
Classifier: Programming Language :: Python :: 3.13
Requires-Python: >=3.11
Requires-Dist: dask<2026,>=2025.11.0
Requires-Dist: ngff-zarr<0.19,>=0.18.2
Requires-Dist: numpy<3,>=2.2.6
Requires-Dist: python-dateutil
Requires-Dist: spatial-image<2,>=1.2.3
Requires-Dist: xarray-dataclass<4,>=3.0.0
Requires-Dist: xarray<2026,>=2025.6.1
Requires-Dist: zarr<4,>=3.1.3
Provides-Extra: dask-image
Requires-Dist: dask-image; extra == 'dask-image'
Provides-Extra: imagej
Requires-Dist: pyimagej; extra == 'imagej'
Provides-Extra: itk
Requires-Dist: itk-filtering>=5.3.0; extra == 'itk'
Provides-Extra: notebooks
Requires-Dist: matplotlib<4,>=3.9.2; extra == 'notebooks'
Requires-Dist: ome-types<0.6,>=0.5.1.post1; extra == 'notebooks'
Requires-Dist: tqdm<5,>=4.66.4; extra == 'notebooks'
Provides-Extra: test
Requires-Dist: fsspec; extra == 'test'
Requires-Dist: jsonschema; extra == 'test'
Requires-Dist: nbmake; extra == 'test'
Requires-Dist: pooch; extra == 'test'
Requires-Dist: pytest; extra == 'test'
Requires-Dist: pytest-mypy; extra == 'test'
Requires-Dist: urllib3; extra == 'test'
